django_confy-1.0.4.dist-info/DESCRIPTION.rst
django_confy-1.0.4.dist-info/top_level.txt
django_confy-1.0.4.dist-info/metadata.json
django_confy-1.0.4.dist-info/RECORD
django_confy-1.0.4.dist-info/WHEEL
django_confy-1.0.4.dist-info/METADATA
django_confy-1.0.4.dist-info/pbr.json
confy/database.py
confy/email.py
confy/__init__.py
confy/cache.py
confy/search.py
confy/apps.py
