Metadata-Version: 2.0
Name: django-confy
Version: 1.0.4
Summary: Django project configuration helpers
Home-page: http://github.com/MechanisM/django-confy
Author: Eugene MechanisM
Author-email: eugene@mechanism.name
License: MIT
Keywords: django,config,env,12factor
Platform: UNKNOWN
Classifier: Development Status :: 4 - Beta
Classifier: Intended Audience :: Developers
Classifier: Topic :: Software Development :: Build Tools
Classifier: License :: OSI Approved :: MIT License
Classifier: Programming Language :: Python :: 2.7
Classifier: Programming Language :: Python :: 3.4
